{"method": ["OAA", "OAA", "OAA", "OAA", "OAA", "OAA", "OAA", "OAA", "OAA", "OAA", "OAA", "OAA", "OAA", "OAA", "OAA", "OAA", "OAA", "OAA", "OAA", "OAA", "OAA", "OAA", "OAA", "OAA", "OAA", "OAA", "OAA", "OAA", "OAA", "OAA", "OAA", "OAA", "OAA", "OAA", "OAA", "OAA", "OAA", "OAA", "OAA", "OAA", "OAA", "OAA", "OAA", "OAA", "OAA", "OAA", "OAA", "OAA", "OAA", "OAA", "OAA", "OAA", "OAA", "OAA", "OAA", "OAA", "OAA", "OAA", "OAA", "OAA", "OAA", "OAA", "OAA", "OAA", "OAA", "OAA", "OAA", "OAA", "OAA", "OAA", "OAA", "OAA", "OAA", "OAA", "OAA", "OAA", "OAA", "OAA", "OAA", "OAA", "RBOAA", "RBOAA", "RBOAA", "RBOAA", "RBOAA", "RBOAA", "RBOAA", "RBOAA", "RBOAA", "RBOAA", "RBOAA", "RBOAA", "RBOAA", "RBOAA", "RBOAA", "RBOAA", "RBOAA", "RBOAA", "RBOAA", "RBOAA", "RBOAA", "RBOAA", "RBOAA", "RBOAA", "RBOAA", "RBOAA", "RBOAA", "RBOAA", "RBOAA", "RBOAA", "RBOAA", "RBOAA", "RBOAA", "RBOAA", "RBOAA", "RBOAA", "RBOAA", "RBOAA", "RBOAA", "RBOAA", "RBOAA", "RBOAA", "RBOAA", "RBOAA", "RBOAA", "RBOAA", "RBOAA", "RBOAA", "RBOAA", "RBOAA", "RBOAA", "RBOAA", "RBOAA", "RBOAA", "RBOAA", "RBOAA", "RBOAA", "RBOAA", "RBOAA", "RBOAA", "RBOAA", "RBOAA", "RBOAA", "RBOAA", "RBOAA", "RBOAA", "RBOAA", "RBOAA", "RBOAA", "RBOAA", "RBOAA", "RBOAA", "RBOAA", "RBOAA", "RBOAA", "RBOAA", "RBOAA", "RBOAA", "RBOAA", "RBOAA", "CAA", "CAA", "CAA", "CAA", "CAA", "CAA", "CAA", "CAA", "CAA", "CAA"], "with_init": [false, false, false, false, false, false, false, false, false, false, true, true, true, true, true, true, true, true, true, true, false, false, false, false, false, false, false, false, false, false, true, true, true, true, true, true, true, true, true, true, false, false, false, false, false, false, false, false, false, false, true, true, true, true, true, true, true, true, true, true, false, false, false, false, false, false, false, false, false, false, true, true, true, true, true, true, true, true, true, true, false, false, false, false, false, false, false, false, false, false, true, true, true, true, true, true, true, true, true, true, false, false, false, false, false, false, false, false, false, false, true, true, true, true, true, true, true, true, true, true, false, false, false, false, false, false, false, false, false, false, true, true, true, true, true, true, true, true, true, true, false, false, false, false, false, false, false, false, false, false, true, true, true, true, true, true, true, true, true, true, false, false, false, false, false, false, false, false, false, false], "beta_reg": [false, false, false, false, false, false, false, false, false, false, false, false, false, false, false, false, false, false, false, false, false, false, false, false, false, false, false, false, false, false, false, false, false, false, false, false, false, false, false, false, true, true, true, true, true, true, true, true, true, true, true, true, true, true, true, true, true, true, true, true, true, true, true, true, true, true, true, true, true, true, true, true, true, true, true, true, true, true, true, true, false, false, false, false, false, false, false, false, false, false, false, false, false, false, false, false, false, false, false, false, false, false, false, false, false, false, false, false, false, false, false, false, false, false, false, false, false, false, false, false, true, true, true, true, true, true, true, true, true, true, true, true, true, true, true, true, true, true, true, true, true, true, true, true, true, true, true, true, true, true, true, true, true, true, true, true, true, true, true, true, false, false, false, false, false, false, false, false, false, false], "alternating": [false, false, false, false, false, false, false, false, false, false, false, false, false, false, false, false, false, false, false, false, true, true, true, true, true, true, true, true, true, true, true, true, true, true, true, true, true, true, true, true, false, false, false, false, false, false, false, false, false, false, false, false, false, false, false, false, false, false, false, false, true, true, true, true, true, true, true, true, true, true, true, true, true, true, true, true, true, true, true, true, false, false, false, false, false, false, false, false, false, false, false, false, false, false, false, false, false, false, false, false, true, true, true, true, true, true, true, true, true, true, true, true, true, true, true, true, true, true, true, true, false, false, false, false, false, false, false, false, false, false, false, false, false, false, false, false, false, false, false, false, true, true, true, true, true, true, true, true, true, true, true, true, true, true, true, true, true, true, true, true, false, false, false, false, false, false, false, false, false, false], "NMI": [0.31105715696023883, 0.31681516615719785, 0.3226297103427722, 0.3164695353163176, 0.318676112575598, 0.41117851939426925, 0.32261042247136795, 0.3107822347233232, 0.3107293260236844, 0.31632904302311404, 0.32133560861791055, 0.3225010701720172, 0.31677378128345035, 0.31674933348237316, 0.32341144864397303, 0.31672113544925784, 0.3234905811143658, 0.3159716237231858, 0.3167379968029659, 0.31676855917491853, 0.31485527525062124, 0.31464499223939346, 0.31493936906891173, 0.3147038474265829, 0.3149360432697769, 0.31486899823882514, 0.31743148826345147, 0.4277802558553758, 0.31491914710053603, 0.31485390247585726, 0.3148349665078928, 0.314825035675151, 0.3148533501019207, 0.3148413857189131, 0.31483685359118097, 0.3148338798129848, 0.31483205615030124, 0.3119640838883803, 0.3148386767738991, 0.31483397234640487, 0.3134392865170497, 0.31300755617861464, 0.3047087044487182, 0.2978692869117888, 0.3134527779061168, 0.3047027514669888, 0.3131113151752093, 0.31589535000539526, 0.3201390192499953, 0.32023462958020044, 0.3143169363634358, 0.31540623881750995, 0.31424782347394653, 0.31437651588839666, 0.31506947603656404, 0.3142895563073477, 0.3146867933724474, 0.3199249931607353, 0.314271154457837, 0.3199365444679902, 0.31453081306198344, 0.31446015956504514, 0.3243440210870917, 0.3092522043017509, 0.3095226014043704, 0.32616084242733634, 0.31448183942778934, 0.3159163771486023, 0.3859703031755615, 0.3207589628105378, 0.32730280139047685, 0.32221606223081184, 0.3272997833315504, 0.327289217884372, 0.32729149176659267, 0.327291338064169, 0.3273028328190657, 0.3272902577718067, 0.32730332656404626, 0.3272966807686658, 0.70138797930197, 0.7287110160891345, 0.7194547670929321, 0.7290325878726976, 0.7250120215819637, 0.7245870954004908, 0.69881708703597, 0.7055296431756752, 0.7204511889336028, 0.739672799833679, 0.7823807563662611, 0.7230327876088612, 0.7808498941314683, 0.7760965792638563, 0.7358738887280821, 0.7809355411421371, 0.7787660667312853, 0.7735314922339219, 0.7186644637589265, 0.7303240141780575, 0.6991937262532398, 0.7374173126850811, 0.6914765949896855, 0.6972091145050374, 0.7125421903767412, 0.7085700530489087, 0.6356093767862702, 0.7588280179656433, 0.7498641548945885, 0.7454248406194157, 0.7285198716121641, 0.7064016671655661, 0.713355841141725, 0.7609857770554707, 0.7701134723007378, 0.6931933559117919, 0.705887073523745, 0.7510822719600493, 0.6444856049056821, 0.6945455498243148, 0.7301713787753245, 0.765978868661468, 0.7838524652155916, 0.7877050641477561, 0.7691384829711742, 0.7922941684487596, 0.7878367089604246, 0.7721787302102611, 0.783940616952698, 0.7851269040323426, 0.7925305907303046, 0.5456103393068112, 0.7521668111680127, 0.8041091313703784, 0.7930813990498117, 0.7952575843725704, 0.6769526812255741, 0.7954029314068244, 0.7969414313116635, 0.7886167988402578, 0.7417894489709644, 0.7456658828480663, 0.7492325531418357, 0.7581965406433517, 0.764651351075019, 0.746466974149791, 0.749161596857733, 0.7631373356575348, 0.7518329265923698, 0.7013548596870575, 0.7879872896254116, 0.7148199387106265, 0.7974648283963838, 0.7920097381373072, 0.7082409998878239, 0.7907990340184737, 0.793953745809394, 0.7752796568977428, 0.6654487018958298, 0.7852995534857558, 0.32478958907284866, 0.3306809568904577, 0.3193993697929043, 0.3193558975596296, 0.4014762614699278, 0.32490890087058705, 0.3226024956427818, 0.31971490300924665, 0.3201632329757133, 0.32264724802876815], "MCC": [0.8261177221922601, 0.8307324043468958, 0.8322314916283525, 0.8301407776242428, 0.8350773735624505, 0.8231692752585321, 0.8331401907505401, 0.8264553595813403, 0.8266468413157965, 0.830548719917505, 0.8350108332128555, 0.832964314179887, 0.8340698139749972, 0.8340362913382586, 0.836306722750714, 0.8340561640421326, 0.8362311953202086, 0.8309043513073676, 0.834066002098318, 0.8340667258007405, 0.8213141260895038, 0.8214178476584184, 0.8212861396936129, 0.821417363347456, 0.8212529775064095, 0.821292861694089, 0.8215623969193565, 0.7487020296712051, 0.8212435695593033, 0.8079702271986241, 0.8212858343489704, 0.821281838996967, 0.8212772174294433, 0.8212742950704257, 0.8212881166572111, 0.8212818526285347, 0.8212758964033672, 0.8111793350743155, 0.821282106621457, 0.8212749051252154, 0.8297993431242237, 0.8315651296605292, 0.8260168634095955, 0.8258256772872293, 0.8293758138521542, 0.8256898154151262, 0.8297912392048375, 0.8328562048828024, 0.8342097952320002, 0.8341102187959814, 0.8293794446761198, 0.8297365280868476, 0.8293708318812111, 0.8294040454773969, 0.8297472834659189, 0.8293897915825493, 0.8297404217283949, 0.8318238698322645, 0.8293877897321787, 0.8318172262370641, 0.8325782076206529, 0.8323665330444777, 0.8359563900464201, 0.8284446795688064, 0.8288493599611951, 0.8377027939956778, 0.8326142490592331, 0.8328978984316541, 0.7922818523634554, 0.7857948568406069, 0.8395506808132152, 0.8425676395163845, 0.8395367276750575, 0.8395283039505467, 0.8395515114467669, 0.8395422534934928, 0.8395473376034217, 0.8395343350366429, 0.8395573353274646, 0.8395502650247421, 0.9559508641875208, 0.93793834191043, 0.9514196193187899, 0.9463359230812086, 0.9343094883521812, 0.9317050548231759, 0.9430734919604502, 0.9392127832796117, 0.8975565645799838, 0.9514032174178437, 0.9487013240989404, 0.9488553080771429, 0.9462399112270944, 0.9378934282530139, 0.9460301711270992, 0.9486037669305384, 0.951036528211767, 0.9470338641460817, 0.9468259102201584, 0.9453524600351626, 0.9412615821096146, 0.9413966410086619, 0.9376038442655146, 0.9436330933187218, 0.9424825042430611, 0.9436071778984331, 0.9403360267189994, 0.9447794035158417, 0.945380320406096, 0.9297419039230369, 0.910024433834636, 0.8778550479628554, 0.8957190020030951, 0.8776863458863424, 0.8883428000773437, 0.8682172715321083, 0.8761181159384309, 0.8786296142565632, 0.8186717577932701, 0.8913747283295831, 0.9342326222119, 0.9403852971599447, 0.9541187706138917, 0.9570950353230154, 0.9517881245943635, 0.945171357383725, 0.9512527696490297, 0.9465223151281754, 0.9453574103090476, 0.9480711362871309, 0.9458402819738175, 0.8770785896959667, 0.9605189065529386, 0.9546666284869417, 0.9438623691366534, 0.9614501509599519, 0.8607308018608602, 0.9436424243529681, 0.9496148498790106, 0.9461702873003602, 0.9437071917156231, 0.9516320615712327, 0.9495449060683968, 0.944507845875215, 0.9457799022619414, 0.948417132997299, 0.94512252077272, 0.9395927471638063, 0.9468215779487869, 0.9508408330314481, 0.9446144194050458, 0.9513722618797562, 0.946275619915753, 0.936763854267958, 0.9449066907589839, 0.9416176896164664, 0.9414627461788997, 0.9336075886231973, 0.9457410695096501, 0.945570350990801, 0.8208903910036058, 0.8316431310983626, 0.8195724029229711, 0.8194628260895184, 0.767103621325632, 0.8208640592453897, 0.8216606207362886, 0.8196792818332211, 0.819777091014628, 0.8217597390797913]}